iridium/__init__.py
iridium/iridium.py
iridium_engine-0.0.0.dist-info/LICENSE
iridium_engine-0.0.0.dist-info/METADATA
iridium_engine-0.0.0.dist-info/WHEEL
iridium_engine-0.0.0.dist-info/top_level.txt
iridium_engine-0.0.0.dist-info/RECORD
