Metadata-Version: 2.1
Name: iridium-engine
Version: 0.0.0
Summary: Iridium Engine
Home-page: https://github.com/mbmgfnbk/Iridium-Engine
Author: Felix Bitsch
Author-email: felix.a.bitsch@gmail.com
License: UNKNOWN
Project-URL: Bug Tracker, https://github.com/mbmgfnbk/Iridium-Engine/issues
Platform: UNKNOWN
Classifier: Programming Language :: Python :: 3
Classifier: License :: OSI Approved :: GNU General Public License v3 (GPLv3)
Classifier: Operating System :: OS Independent
Requires-Python: >=3.10
License-File: LICENSE
